odoo/addons/account_move_line_repair_info/README.rst
odoo/addons/account_move_line_repair_info/__init__.py
odoo/addons/account_move_line_repair_info/__manifest__.py
odoo/addons/account_move_line_repair_info/hooks.py
odoo/addons/account_move_line_repair_info/i18n/account_move_line_repair_info.pot
odoo/addons/account_move_line_repair_info/i18n/es.po
odoo/addons/account_move_line_repair_info/models/__init__.py
odoo/addons/account_move_line_repair_info/models/account_move.py
odoo/addons/account_move_line_repair_info/models/repair_order.py
odoo/addons/account_move_line_repair_info/models/stock_move.py
odoo/addons/account_move_line_repair_info/readme/CONTRIBUTORS.rst
odoo/addons/account_move_line_repair_info/readme/DESCRIPTION.rst
odoo/addons/account_move_line_repair_info/readme/USAGE.rst
odoo/addons/account_move_line_repair_info/security/account_security.xml
odoo/addons/account_move_line_repair_info/static/description/icon.png
odoo/addons/account_move_line_repair_info/static/description/index.html
odoo/addons/account_move_line_repair_info/tests/__init__.py
odoo/addons/account_move_line_repair_info/tests/test_account_move_line_repair_info.py
odoo/addons/account_move_line_repair_info/views/account_move_view.xml
odoo14_addon_account_move_line_repair_info-14.0.1.0.1.dev6.dist-info/METADATA
odoo14_addon_account_move_line_repair_info-14.0.1.0.1.dev6.dist-info/WHEEL
odoo14_addon_account_move_line_repair_info-14.0.1.0.1.dev6.dist-info/top_level.txt
odoo14_addon_account_move_line_repair_info-14.0.1.0.1.dev6.dist-info/RECORD
